odsc_default_sphinx_theme/__init__.py
odsc_default_sphinx_theme/theme.toml
odsc_default_sphinx_theme/static/ods_logo_dark.svg
odsc_default_sphinx_theme/static/ods_logo_light.svg
odsc_default_sphinx_theme-0.1.1.dist-info/licenses/LICENSE
odsc_default_sphinx_theme-0.1.1.dist-info/METADATA
odsc_default_sphinx_theme-0.1.1.dist-info/WHEEL
odsc_default_sphinx_theme-0.1.1.dist-info/entry_points.txt
odsc_default_sphinx_theme-0.1.1.dist-info/top_level.txt
odsc_default_sphinx_theme-0.1.1.dist-info/RECORD
