Metadata-Version: 2.4
Name: odsc_default_sphinx_theme
Version: 0.1.1
Home-page: https://github.com/OpenDataServices/odsc_default_sphinx_theme
Author: Open Data Services
Author-email: code@opendataservices.coop
License-File: LICENSE
Requires-Dist: furo
Dynamic: author
Dynamic: author-email
Dynamic: home-page
Dynamic: license-file
Dynamic: requires-dist
